{"inventory":{"category":"","date":"2019-02-23 22:22:29","brand":"Supreme Formula","name":"Supreme Formula Crewneck Navy","SKU":"N/A","retail":"","shippingCost":"","color":"","size":"L","condition":"new","notes":""},"sale":{"market":"StockX","orderNum":"4552219-4451978","trackingNum":"","saleDate":"2019-02-23 22:22:29","soldPrice":"215","totalAfterFees":"190.2750","notes":""},"expense":{"expenseName":"","expensePrice":"","expenseReason":"","expenseDateStart":"","expenseOccurance":"","expenseEnded":"","expenseNotes":""},"cside":{"customerId":"","pic":"","itemId":"","currentLowestAsk":""}}