{"inventory":{"category":"","date":"04/06/2019","brand":"nike air skylon ll/fog","name":"nike air skylon ll/fog","SKU":"bq2752 003","retail":"","shippingCost":"","color":"light bone/clear-reflect","size":"10.5","condition":"new","notes":"NY"},"sale":{"market":"Flightclub","orderNum":"3056546","trackingNum":"","saleDate":"04/09/2019","soldPrice":"210.00","totalAfterFees":"173.25","notes":"NY"},"expense":{"expenseName":"","expensePrice":"","expenseReason":"","expenseDateStart":"","expenseOccurance":"","expenseEnded":"","expenseNotes":""},"cside":{"customerId":"","pic":"","itemId":"","currentLowestAsk":""}}