{"inventory":{"category":"","date":"2018-11-08 16:09:44","brand":"Supreme LACOSTE","name":"Supreme LACOSTE Crewneck Pink","SKU":"N/A","retail":"","shippingCost":"","color":"","size":"M","condition":"new","notes":""},"sale":{"market":"StockX","orderNum":"3064801-2964560","trackingNum":"","saleDate":"2018-11-08 16:09:44","soldPrice":"230","totalAfterFees":"202.4000","notes":""},"expense":{"expenseName":"","expensePrice":"","expenseReason":"","expenseDateStart":"","expenseOccurance":"","expenseEnded":"","expenseNotes":""},"cside":{"customerId":"","pic":"","itemId":"","currentLowestAsk":""}}