{"inventory":{"category":"LISTED,UNSOLD","date":"4/24/2019","brand":"24189","name":"WMNS Air Jordan 1 High OG NRG","SKU":"BV2613 600","retail":"","shippingCost":"","color":"BORDEAUX/LT ARMORY BLUE","size":"80","condition":"new","notes":"SHPCAP1051243; SIN471393"},"sale":{"market":"Stadium Goods","orderNum":"","trackingNum":"RECSGD088113","saleDate":"PENDING","soldPrice":"240.00","totalAfterFees":"192.00","notes":"SHPCAP1051243; SIN471393"},"expense":{"expenseName":"","expensePrice":"","expenseReason":"","expenseDateStart":"","expenseOccurance":"","expenseEnded":"","expenseNotes":""},"cside":{"customerId":"","pic":"","itemId":"","currentLowestAsk":""}}