{"inventory":{"category":"LISTED,UNSOLD","date":"08/03/2019","brand":"yeezy boost 350 v2","name":"yeezy boost 350 v2","SKU":"eg7490","retail":220,"shippingCost":"","color":"clay/clay/clay","size":"4","condition":"new","notes":"NY"},"sale":{"market":"Flightclub","orderNum":"3368285","trackingNum":"","saleDate":"PENDING","soldPrice":"390.00","totalAfterFees":"321.75","notes":"NY"},"expense":{"expenseName":"","expensePrice":"","expenseReason":"","expenseDateStart":"","expenseOccurance":"","expenseEnded":"","expenseNotes":""},"cside":{"customerId":"","pic":"","itemId":"","currentLowestAsk":""}}